agents_extensions/__init__.py
agents_extensions/py.typed
agents_extensions/memory/__init__.py
agents_extensions/memory/postgresql_session.py
agents_extensions-0.0.1.dist-info/METADATA
agents_extensions-0.0.1.dist-info/WHEEL
agents_extensions-0.0.1.dist-info/licenses/LICENSE
agents_extensions-0.0.1.dist-info/RECORD
