Metadata-Version: 2.4
Name: agents-extensions
Version: 0.0.1
Summary: Extends the functionality of the OpenAI Agents Python SDK.
Author-email: roman-collinge <romancollinge@outlook.com>
License-File: LICENSE
Requires-Python: >=3.12
Requires-Dist: asyncpg>=0.30.0
Requires-Dist: openai-agents>=0.2.4
